microplex/__init__.py
microplex/discrete.py
microplex/flows.py
microplex/synthesizer.py
microplex/transforms.py
microplex-0.1.0.dist-info/METADATA
microplex-0.1.0.dist-info/WHEEL
microplex-0.1.0.dist-info/licenses/LICENSE
microplex-0.1.0.dist-info/RECORD
