Metadata-Version: 2.4
Name: microplex
Version: 0.1.0
Summary: Microdata synthesis and reweighting using normalizing flows
Project-URL: Homepage, https://github.com/CosilicoAI/microplex
Project-URL: Documentation, https://cosilicoai.github.io/microplex
Project-URL: Repository, https://github.com/CosilicoAI/microplex
Author-email: Cosilico <hello@cosilico.ai>
License-Expression: MIT
License-File: LICENSE
Keywords: imputation,microdata,normalizing-flows,privacy,survey-data,synthesis
Classifier: Development Status :: 3 - Alpha
Classifier: Intended Audience :: Science/Research
Classifier: License :: OSI Approved :: MIT License
Classifier: Programming Language :: Python :: 3
Classifier: Programming Language :: Python :: 3.10
Classifier: Programming Language :: Python :: 3.11
Classifier: Programming Language :: Python :: 3.12
Classifier: Topic :: Scientific/Engineering :: Artificial Intelligence
Classifier: Topic :: Scientific/Engineering :: Information Analysis
Requires-Python: >=3.10
Requires-Dist: numpy>=1.24
Requires-Dist: pandas>=2.0
Requires-Dist: scipy>=1.10
Requires-Dist: torch>=2.0
Provides-Extra: all
Requires-Dist: jupyter-book>=0.15; extra == 'all'
Requires-Dist: matplotlib>=3.7; extra == 'all'
Requires-Dist: mypy>=1.0; extra == 'all'
Requires-Dist: myst-nb>=0.17; extra == 'all'
Requires-Dist: pytest-cov>=4.0; extra == 'all'
Requires-Dist: pytest>=7.0; extra == 'all'
Requires-Dist: ruff>=0.1; extra == 'all'
Requires-Dist: scikit-learn>=1.3; extra == 'all'
Requires-Dist: sdv>=1.0; extra == 'all'
Requires-Dist: seaborn>=0.12; extra == 'all'
Requires-Dist: sphinx-autodoc-typehints>=1.23; extra == 'all'
Requires-Dist: sphinx>=6.0; extra == 'all'
Provides-Extra: benchmark
Requires-Dist: matplotlib>=3.7; extra == 'benchmark'
Requires-Dist: scikit-learn>=1.3; extra == 'benchmark'
Requires-Dist: sdv>=1.0; extra == 'benchmark'
Requires-Dist: seaborn>=0.12; extra == 'benchmark'
Provides-Extra: dev
Requires-Dist: mypy>=1.0; extra == 'dev'
Requires-Dist: pytest-cov>=4.0; extra == 'dev'
Requires-Dist: pytest>=7.0; extra == 'dev'
Requires-Dist: ruff>=0.1; extra == 'dev'
Provides-Extra: docs
Requires-Dist: jupyter-book>=0.15; extra == 'docs'
Requires-Dist: myst-nb>=0.17; extra == 'docs'
Requires-Dist: sphinx-autodoc-typehints>=1.23; extra == 'docs'
Requires-Dist: sphinx>=6.0; extra == 'docs'
